{
  "poi_connections": {},
  "node_sequences": {
    "4f535780-1419-4177-872b-5189ed395fe9": {
      "path_id": "4f535780-1419-4177-872b-5189ed395fe9",
      "nodes": [
        "起始位置_39.904200_116.407400",
        "道路位置_39.904026_116.407408"
      ],
      "coordinates": [
        [
          0.0,
          0.0
        ],
        [
          0.0,
          0.0
        ]
      ],
      "poi_waypoints": [],
      "start_location": [
        39.9042,
        116.4074
      ],
      "end_location": [
        39.904025779970134,
        116.40740775681562
      ],
      "total_distance": 19.38367939306239,
      "node_count": 2,
      "created_time": "2025-11-15T21:55:10.144279",
      "traversal_count": 1
    },
    "03c827ba-852c-4406-982e-eb78e9e9f906": {
      "path_id": "03c827ba-852c-4406-982e-eb78e9e9f906",
      "nodes": [
        "起始_39.903994_116.406703",
        "路径点_39.903994_116.406703"
      ],
      "coordinates": [
        [
          0.0,
          0.0
        ],
        [
          0.0,
          0.0
        ]
      ],
      "poi_waypoints": [],
      "start_location": [
        39.90399442000006,
        116.40670340400004
      ],
      "end_location": [
        39.90399442000006,
        116.40670340400004
      ],
      "total_distance": 0.0,
      "node_count": 2,
      "created_time": "2025-11-15T21:55:13.651492",
      "traversal_count": 1
    },
    "3dc451ec-8d2a-4b2b-b5dc-02b4753c49cd": {
      "path_id": "3dc451ec-8d2a-4b2b-b5dc-02b4753c49cd",
      "nodes": [
        "起始位置_39.903994_116.406703",
        "道路位置_39.903994_116.406703"
      ],
      "coordinates": [
        [
          0.0,
          0.0
        ],
        [
          0.0,
          0.0
        ]
      ],
      "poi_waypoints": [],
      "start_location": [
        39.90399442000006,
        116.40670340400004
      ],
      "end_location": [
        39.90399442000006,
        116.40670340400004
      ],
      "total_distance": 0.0,
      "node_count": 2,
      "created_time": "2025-11-15T21:55:13.658039",
      "traversal_count": 1
    },
    "e6508c2f-590b-4670-81cb-5867bfb798ff": {
      "path_id": "e6508c2f-590b-4670-81cb-5867bfb798ff",
      "nodes": [
        "起始_39.906138_116.406611",
        "路径点_39.906138_116.406611"
      ],
      "coordinates": [
        [
          0.0,
          0.0
        ],
        [
          0.0,
          0.0
        ]
      ],
      "poi_waypoints": [],
      "start_location": [
        39.90613805100003,
        116.40661135700009
      ],
      "end_location": [
        39.90613805100003,
        116.40661135700009
      ],
      "total_distance": 0.0,
      "node_count": 2,
      "created_time": "2025-11-15T21:55:16.083417",
      "traversal_count": 1
    },
    "dd1222e1-315e-4b54-96ea-dea89c569046": {
      "path_id": "dd1222e1-315e-4b54-96ea-dea89c569046",
      "nodes": [
        "起始位置_39.906138_116.406611",
        "道路位置_39.906138_116.406611"
      ],
      "coordinates": [
        [
          0.0,
          0.0
        ],
        [
          0.0,
          0.0
        ]
      ],
      "poi_waypoints": [],
      "start_location": [
        39.90613805100003,
        116.40661135700009
      ],
      "end_location": [
        39.90613805100003,
        116.40661135700009
      ],
      "total_distance": 0.0,
      "node_count": 2,
      "created_time": "2025-11-15T21:55:16.089468",
      "traversal_count": 1
    },
    "9547f14b-8d37-46c8-875b-a8c5ea3f490c": {
      "path_id": "9547f14b-8d37-46c8-875b-a8c5ea3f490c",
      "nodes": [
        "起始_39.906180_116.407600",
        "路径点_39.906180_116.407600"
      ],
      "coordinates": [
        [
          0.0,
          0.0
        ],
        [
          0.0,
          0.0
        ]
      ],
      "poi_waypoints": [],
      "start_location": [
        39.90618000000006,
        116.40760000000012
      ],
      "end_location": [
        39.90618000000006,
        116.40760000000012
      ],
      "total_distance": 0.0,
      "node_count": 2,
      "created_time": "2025-11-15T21:55:17.913232",
      "traversal_count": 1
    },
    "ce974c7a-837d-4892-893d-18989fe15d3c": {
      "path_id": "ce974c7a-837d-4892-893d-18989fe15d3c",
      "nodes": [
        "起始位置_39.906180_116.407600",
        "道路位置_39.906180_116.407600"
      ],
      "coordinates": [
        [
          0.0,
          0.0
        ],
        [
          0.0,
          0.0
        ]
      ],
      "poi_waypoints": [],
      "start_location": [
        39.90618000000006,
        116.40760000000012
      ],
      "end_location": [
        39.90618000000006,
        116.40760000000012
      ],
      "total_distance": 0.0,
      "node_count": 2,
      "created_time": "2025-11-15T21:55:17.919820",
      "traversal_count": 1
    },
    "57a08709-c99d-4422-8b5b-f7af41e05465": {
      "path_id": "57a08709-c99d-4422-8b5b-f7af41e05465",
      "nodes": [
        "决策位置_39.906180_116.407600"
      ],
      "coordinates": [
        [
          0.0,
          0.0
        ]
      ],
      "poi_waypoints": [],
      "start_location": [
        39.90618000000006,
        116.40760000000012
      ],
      "end_location": [
        39.90618000000006,
        116.40760000000012
      ],
      "total_distance": 0.0,
      "node_count": 1,
      "created_time": "2025-11-15T21:55:17.921804",
      "traversal_count": 1
    },
    "f4e2c6d6-1117-454d-b2af-ebfb55f6d8db": {
      "path_id": "f4e2c6d6-1117-454d-b2af-ebfb55f6d8db",
      "nodes": [
        "起始_39.906138_116.406611",
        "路径点_39.906138_116.406611"
      ],
      "coordinates": [
        [
          0.0,
          0.0
        ],
        [
          0.0,
          0.0
        ]
      ],
      "poi_waypoints": [],
      "start_location": [
        39.90613805100003,
        116.40661135700009
      ],
      "end_location": [
        39.90613805100003,
        116.40661135700009
      ],
      "total_distance": 0.0,
      "node_count": 2,
      "created_time": "2025-11-15T21:55:24.757797",
      "traversal_count": 1
    },
    "b794cbdb-a3ad-4be0-bb2d-1b7e64b652b7": {
      "path_id": "b794cbdb-a3ad-4be0-bb2d-1b7e64b652b7",
      "nodes": [
        "起始位置_39.906138_116.406611",
        "道路位置_39.906138_116.406611"
      ],
      "coordinates": [
        [
          0.0,
          0.0
        ],
        [
          0.0,
          0.0
        ]
      ],
      "poi_waypoints": [],
      "start_location": [
        39.90613805100003,
        116.40661135700009
      ],
      "end_location": [
        39.90613805100003,
        116.40661135700009
      ],
      "total_distance": 0.0,
      "node_count": 2,
      "created_time": "2025-11-15T21:55:24.764294",
      "traversal_count": 1
    }
  },
  "road_segments": {
    "fe5c802c-a01d-464e-8d4b-410e59807c2e": {
      "segment_id": "fe5c802c-a01d-464e-8d4b-410e59807c2e",
      "start_node": "起始位置_39.904200_116.407400",
      "end_node": "道路位置_39.904026_116.407408",
      "length": 19.38367939306239,
      "road_type": "调整路径",
      "road_name": "",
      "coordinates": [
        [
          39.9042,
          116.4074
        ],
        [
          39.904025779970134,
          116.40740775681562
        ]
      ],
      "traversal_count": 1,
      "created_time": "2025-11-15T21:55:10.144279",
      "last_traversed": "2025-11-15T21:55:10.144279",
      "speed_limit": 0,
      "road_condition": "良好"
    },
    "88e327f6-2fd0-43ee-b447-7107c77322c4": {
      "segment_id": "88e327f6-2fd0-43ee-b447-7107c77322c4",
      "start_node": "起始_39.903994_116.406703",
      "end_node": "路径点_39.903994_116.406703",
      "length": 0.0,
      "road_type": "路径移动",
      "road_name": "",
      "coordinates": [
        [
          39.90399442000006,
          116.40670340400004
        ],
        [
          39.90399442000006,
          116.40670340400004
        ]
      ],
      "traversal_count": 1,
      "created_time": "2025-11-15T21:55:13.651492",
      "last_traversed": "2025-11-15T21:55:13.651492",
      "speed_limit": 0,
      "road_condition": "良好"
    },
    "55386040-900e-496c-ae20-15b16157454e": {
      "segment_id": "55386040-900e-496c-ae20-15b16157454e",
      "start_node": "起始位置_39.903994_116.406703",
      "end_node": "道路位置_39.903994_116.406703",
      "length": 0.0,
      "road_type": "调整路径",
      "road_name": "",
      "coordinates": [
        [
          39.90399442000006,
          116.40670340400004
        ],
        [
          39.90399442000006,
          116.40670340400004
        ]
      ],
      "traversal_count": 1,
      "created_time": "2025-11-15T21:55:13.658039",
      "last_traversed": "2025-11-15T21:55:13.658039",
      "speed_limit": 0,
      "road_condition": "良好"
    },
    "514535fb-d236-4a17-836a-2ffbdec961ff": {
      "segment_id": "514535fb-d236-4a17-836a-2ffbdec961ff",
      "start_node": "起始_39.906138_116.406611",
      "end_node": "路径点_39.906138_116.406611",
      "length": 0.0,
      "road_type": "路径移动",
      "road_name": "",
      "coordinates": [
        [
          39.90613805100003,
          116.40661135700009
        ],
        [
          39.90613805100003,
          116.40661135700009
        ]
      ],
      "traversal_count": 1,
      "created_time": "2025-11-15T21:55:16.083417",
      "last_traversed": "2025-11-15T21:55:16.083417",
      "speed_limit": 0,
      "road_condition": "良好"
    },
    "16de45a2-e67b-4f2a-9c81-d9bc0bad55bb": {
      "segment_id": "16de45a2-e67b-4f2a-9c81-d9bc0bad55bb",
      "start_node": "起始位置_39.906138_116.406611",
      "end_node": "道路位置_39.906138_116.406611",
      "length": 0.0,
      "road_type": "调整路径",
      "road_name": "",
      "coordinates": [
        [
          39.90613805100003,
          116.40661135700009
        ],
        [
          39.90613805100003,
          116.40661135700009
        ]
      ],
      "traversal_count": 1,
      "created_time": "2025-11-15T21:55:16.089468",
      "last_traversed": "2025-11-15T21:55:16.090483",
      "speed_limit": 0,
      "road_condition": "良好"
    },
    "7e5411df-4287-42d0-b502-0ac0c85b6f34": {
      "segment_id": "7e5411df-4287-42d0-b502-0ac0c85b6f34",
      "start_node": "起始_39.906180_116.407600",
      "end_node": "路径点_39.906180_116.407600",
      "length": 0.0,
      "road_type": "路径移动",
      "road_name": "",
      "coordinates": [
        [
          39.90618000000006,
          116.40760000000012
        ],
        [
          39.90618000000006,
          116.40760000000012
        ]
      ],
      "traversal_count": 1,
      "created_time": "2025-11-15T21:55:17.913232",
      "last_traversed": "2025-11-15T21:55:17.913232",
      "speed_limit": 0,
      "road_condition": "良好"
    },
    "94f7365e-c049-4556-b48a-dbe52dabb312": {
      "segment_id": "94f7365e-c049-4556-b48a-dbe52dabb312",
      "start_node": "起始位置_39.906180_116.407600",
      "end_node": "道路位置_39.906180_116.407600",
      "length": 0.0,
      "road_type": "调整路径",
      "road_name": "",
      "coordinates": [
        [
          39.90618000000006,
          116.40760000000012
        ],
        [
          39.90618000000006,
          116.40760000000012
        ]
      ],
      "traversal_count": 1,
      "created_time": "2025-11-15T21:55:17.919820",
      "last_traversed": "2025-11-15T21:55:17.919820",
      "speed_limit": 0,
      "road_condition": "良好"
    },
    "6d3d45d7-ede4-4ac7-954f-dac7977f2af5": {
      "segment_id": "6d3d45d7-ede4-4ac7-954f-dac7977f2af5",
      "start_node": "segment_start_0",
      "end_node": "segment_end_0",
      "length": 0,
      "road_type": "决策节点",
      "road_name": "",
      "coordinates": [
        [
          39.90618000000006,
          116.40760000000012
        ]
      ],
      "traversal_count": 1,
      "created_time": "2025-11-15T21:55:17.921804",
      "last_traversed": "2025-11-15T21:55:17.921804",
      "speed_limit": 0,
      "road_condition": "良好"
    },
    "00b85f69-b8ce-47b5-9a3f-9a0e1e59b117": {
      "segment_id": "00b85f69-b8ce-47b5-9a3f-9a0e1e59b117",
      "start_node": "起始_39.906138_116.406611",
      "end_node": "路径点_39.906138_116.406611",
      "length": 0.0,
      "road_type": "路径移动",
      "road_name": "",
      "coordinates": [
        [
          39.90613805100003,
          116.40661135700009
        ],
        [
          39.90613805100003,
          116.40661135700009
        ]
      ],
      "traversal_count": 1,
      "created_time": "2025-11-15T21:55:24.757797",
      "last_traversed": "2025-11-15T21:55:24.757797",
      "speed_limit": 0,
      "road_condition": "良好"
    },
    "b7eca16b-3bf5-4139-acd9-346ff6fbfa35": {
      "segment_id": "b7eca16b-3bf5-4139-acd9-346ff6fbfa35",
      "start_node": "起始位置_39.906138_116.406611",
      "end_node": "道路位置_39.906138_116.406611",
      "length": 0.0,
      "road_type": "调整路径",
      "road_name": "",
      "coordinates": [
        [
          39.90613805100003,
          116.40661135700009
        ],
        [
          39.90613805100003,
          116.40661135700009
        ]
      ],
      "traversal_count": 1,
      "created_time": "2025-11-15T21:55:24.764294",
      "last_traversed": "2025-11-15T21:55:24.764294",
      "speed_limit": 0,
      "road_condition": "良好"
    }
  },
  "metadata": {
    "saved_time": "2025-11-15T21:55:24.764294",
    "operation_count": 10,
    "stats": {
      "poi_layer": {
        "total_connections": 0,
        "unique_pois": 0,
        "memory_type": "POI层记忆"
      },
      "node_layer": {
        "total_paths": 10,
        "total_nodes": 15,
        "average_path_length": 1.9,
        "total_distance": 19.38,
        "memory_type": "道路节点层记忆"
      },
      "road_layer": {
        "total_segments": 10,
        "total_nodes": 16,
        "total_distance": 19.38,
        "road_types": {
          "调整路径": {
            "count": 5,
            "total_length": 19.38367939306239
          },
          "路径移动": {
            "count": 4,
            "total_length": 0.0
          },
          "决策节点": {
            "count": 1,
            "total_length": 0
          }
        },
        "average_segment_length": 1.94,
        "memory_type": "道路数据层记忆"
      },
      "total_operations": 10,
      "last_updated": "2025-11-15T21:55:24.764294"
    }
  }
}