{
  "poi_connections": {},
  "node_sequences": {
    "370f55c8-46ce-4677-9436-03ad818d6fae": {
      "path_id": "370f55c8-46ce-4677-9436-03ad818d6fae",
      "nodes": [
        "起始位置_39.904200_116.407400",
        "道路位置_39.904026_116.407408"
      ],
      "coordinates": [
        [
          0.0,
          0.0
        ],
        [
          0.0,
          0.0
        ]
      ],
      "poi_waypoints": [],
      "start_location": [
        39.9042,
        116.4074
      ],
      "end_location": [
        39.904025779970134,
        116.40740775681562
      ],
      "total_distance": 19.38367939306239,
      "node_count": 2,
      "created_time": "2025-11-10T21:23:58.625339",
      "traversal_count": 1
    },
    "2b48ca45-be6b-4ee1-b266-d309e64e6b82": {
      "path_id": "2b48ca45-be6b-4ee1-b266-d309e64e6b82",
      "nodes": [
        "起始_39.903994_116.406703",
        "路径点_39.903994_116.406703"
      ],
      "coordinates": [
        [
          0.0,
          0.0
        ],
        [
          0.0,
          0.0
        ]
      ],
      "poi_waypoints": [],
      "start_location": [
        39.90399442000006,
        116.40670340400004
      ],
      "end_location": [
        39.90399442000006,
        116.40670340400004
      ],
      "total_distance": 0.0,
      "node_count": 2,
      "created_time": "2025-11-10T21:24:01.607221",
      "traversal_count": 1
    },
    "762c1efe-f3d9-470a-a183-257090d6b3a2": {
      "path_id": "762c1efe-f3d9-470a-a183-257090d6b3a2",
      "nodes": [
        "起始位置_39.903994_116.406703",
        "道路位置_39.903994_116.406703"
      ],
      "coordinates": [
        [
          0.0,
          0.0
        ],
        [
          0.0,
          0.0
        ]
      ],
      "poi_waypoints": [],
      "start_location": [
        39.90399442000006,
        116.40670340400004
      ],
      "end_location": [
        39.90399442000006,
        116.40670340400004
      ],
      "total_distance": 0.0,
      "node_count": 2,
      "created_time": "2025-11-10T21:24:01.613812",
      "traversal_count": 1
    },
    "15e6d6f2-0f38-4b90-a512-f227af27a62c": {
      "path_id": "15e6d6f2-0f38-4b90-a512-f227af27a62c",
      "nodes": [
        "起始_39.906138_116.406611",
        "路径点_39.906138_116.406611"
      ],
      "coordinates": [
        [
          0.0,
          0.0
        ],
        [
          0.0,
          0.0
        ]
      ],
      "poi_waypoints": [],
      "start_location": [
        39.90613805100003,
        116.40661135700009
      ],
      "end_location": [
        39.90613805100003,
        116.40661135700009
      ],
      "total_distance": 0.0,
      "node_count": 2,
      "created_time": "2025-11-10T21:24:04.035979",
      "traversal_count": 1
    },
    "d328e314-5df3-4f3d-acfc-c8c84129d945": {
      "path_id": "d328e314-5df3-4f3d-acfc-c8c84129d945",
      "nodes": [
        "起始位置_39.906138_116.406611",
        "道路位置_39.906138_116.406611"
      ],
      "coordinates": [
        [
          0.0,
          0.0
        ],
        [
          0.0,
          0.0
        ]
      ],
      "poi_waypoints": [],
      "start_location": [
        39.90613805100003,
        116.40661135700009
      ],
      "end_location": [
        39.90613805100003,
        116.40661135700009
      ],
      "total_distance": 0.0,
      "node_count": 2,
      "created_time": "2025-11-10T21:24:04.043065",
      "traversal_count": 1
    },
    "c734ee85-1386-4bdb-b87c-ea43f6c7d265": {
      "path_id": "c734ee85-1386-4bdb-b87c-ea43f6c7d265",
      "nodes": [
        "起始_39.906180_116.407600",
        "路径点_39.906180_116.407600"
      ],
      "coordinates": [
        [
          0.0,
          0.0
        ],
        [
          0.0,
          0.0
        ]
      ],
      "poi_waypoints": [],
      "start_location": [
        39.90618000000006,
        116.40760000000012
      ],
      "end_location": [
        39.90618000000006,
        116.40760000000012
      ],
      "total_distance": 0.0,
      "node_count": 2,
      "created_time": "2025-11-10T21:24:05.874145",
      "traversal_count": 1
    },
    "ea12120b-a14d-4e16-b11a-74fd05fa0e34": {
      "path_id": "ea12120b-a14d-4e16-b11a-74fd05fa0e34",
      "nodes": [
        "起始位置_39.906180_116.407600",
        "道路位置_39.906180_116.407600"
      ],
      "coordinates": [
        [
          0.0,
          0.0
        ],
        [
          0.0,
          0.0
        ]
      ],
      "poi_waypoints": [],
      "start_location": [
        39.90618000000006,
        116.40760000000012
      ],
      "end_location": [
        39.90618000000006,
        116.40760000000012
      ],
      "total_distance": 0.0,
      "node_count": 2,
      "created_time": "2025-11-10T21:24:05.880776",
      "traversal_count": 1
    },
    "c395e6b0-84b8-4b55-8173-622f38ef331f": {
      "path_id": "c395e6b0-84b8-4b55-8173-622f38ef331f",
      "nodes": [
        "决策位置_39.906180_116.407600"
      ],
      "coordinates": [
        [
          0.0,
          0.0
        ]
      ],
      "poi_waypoints": [],
      "start_location": [
        39.90618000000006,
        116.40760000000012
      ],
      "end_location": [
        39.90618000000006,
        116.40760000000012
      ],
      "total_distance": 0.0,
      "node_count": 1,
      "created_time": "2025-11-10T21:24:05.881782",
      "traversal_count": 1
    },
    "11ef82e2-88a1-4340-9a10-ee393b2254ae": {
      "path_id": "11ef82e2-88a1-4340-9a10-ee393b2254ae",
      "nodes": [
        "起始_39.906138_116.406611",
        "路径点_39.906138_116.406611"
      ],
      "coordinates": [
        [
          0.0,
          0.0
        ],
        [
          0.0,
          0.0
        ]
      ],
      "poi_waypoints": [],
      "start_location": [
        39.90613805100003,
        116.40661135700009
      ],
      "end_location": [
        39.90613805100003,
        116.40661135700009
      ],
      "total_distance": 0.0,
      "node_count": 2,
      "created_time": "2025-11-10T21:24:12.736632",
      "traversal_count": 1
    },
    "3dff2d9c-f7b8-47f1-8ce1-c61511d420d8": {
      "path_id": "3dff2d9c-f7b8-47f1-8ce1-c61511d420d8",
      "nodes": [
        "起始位置_39.906138_116.406611",
        "道路位置_39.906138_116.406611"
      ],
      "coordinates": [
        [
          0.0,
          0.0
        ],
        [
          0.0,
          0.0
        ]
      ],
      "poi_waypoints": [],
      "start_location": [
        39.90613805100003,
        116.40661135700009
      ],
      "end_location": [
        39.90613805100003,
        116.40661135700009
      ],
      "total_distance": 0.0,
      "node_count": 2,
      "created_time": "2025-11-10T21:24:12.740798",
      "traversal_count": 1
    }
  },
  "road_segments": {
    "b1639d39-9980-4640-af7a-073ca87a0a9b": {
      "segment_id": "b1639d39-9980-4640-af7a-073ca87a0a9b",
      "start_node": "起始位置_39.904200_116.407400",
      "end_node": "道路位置_39.904026_116.407408",
      "length": 19.38367939306239,
      "road_type": "调整路径",
      "road_name": "",
      "coordinates": [
        [
          39.9042,
          116.4074
        ],
        [
          39.904025779970134,
          116.40740775681562
        ]
      ],
      "traversal_count": 1,
      "created_time": "2025-11-10T21:23:58.625339",
      "last_traversed": "2025-11-10T21:23:58.625339",
      "speed_limit": 0,
      "road_condition": "良好"
    },
    "e0df00e8-57a6-4bea-821a-e9c2682219b2": {
      "segment_id": "e0df00e8-57a6-4bea-821a-e9c2682219b2",
      "start_node": "起始_39.903994_116.406703",
      "end_node": "路径点_39.903994_116.406703",
      "length": 0.0,
      "road_type": "路径移动",
      "road_name": "",
      "coordinates": [
        [
          39.90399442000006,
          116.40670340400004
        ],
        [
          39.90399442000006,
          116.40670340400004
        ]
      ],
      "traversal_count": 1,
      "created_time": "2025-11-10T21:24:01.607221",
      "last_traversed": "2025-11-10T21:24:01.607221",
      "speed_limit": 0,
      "road_condition": "良好"
    },
    "c4a8ac4d-fefb-4d94-9bd9-771e3bb1f81a": {
      "segment_id": "c4a8ac4d-fefb-4d94-9bd9-771e3bb1f81a",
      "start_node": "起始位置_39.903994_116.406703",
      "end_node": "道路位置_39.903994_116.406703",
      "length": 0.0,
      "road_type": "调整路径",
      "road_name": "",
      "coordinates": [
        [
          39.90399442000006,
          116.40670340400004
        ],
        [
          39.90399442000006,
          116.40670340400004
        ]
      ],
      "traversal_count": 1,
      "created_time": "2025-11-10T21:24:01.613812",
      "last_traversed": "2025-11-10T21:24:01.613812",
      "speed_limit": 0,
      "road_condition": "良好"
    },
    "7a8df35b-c048-41f8-aacb-afecdc4814f2": {
      "segment_id": "7a8df35b-c048-41f8-aacb-afecdc4814f2",
      "start_node": "起始_39.906138_116.406611",
      "end_node": "路径点_39.906138_116.406611",
      "length": 0.0,
      "road_type": "路径移动",
      "road_name": "",
      "coordinates": [
        [
          39.90613805100003,
          116.40661135700009
        ],
        [
          39.90613805100003,
          116.40661135700009
        ]
      ],
      "traversal_count": 1,
      "created_time": "2025-11-10T21:24:04.035979",
      "last_traversed": "2025-11-10T21:24:04.035979",
      "speed_limit": 0,
      "road_condition": "良好"
    },
    "5fabcd31-01a5-4817-9f62-f02b604ce962": {
      "segment_id": "5fabcd31-01a5-4817-9f62-f02b604ce962",
      "start_node": "起始位置_39.906138_116.406611",
      "end_node": "道路位置_39.906138_116.406611",
      "length": 0.0,
      "road_type": "调整路径",
      "road_name": "",
      "coordinates": [
        [
          39.90613805100003,
          116.40661135700009
        ],
        [
          39.90613805100003,
          116.40661135700009
        ]
      ],
      "traversal_count": 1,
      "created_time": "2025-11-10T21:24:04.043065",
      "last_traversed": "2025-11-10T21:24:04.043065",
      "speed_limit": 0,
      "road_condition": "良好"
    },
    "cb35effc-2248-4617-beec-974c6862282e": {
      "segment_id": "cb35effc-2248-4617-beec-974c6862282e",
      "start_node": "起始_39.906180_116.407600",
      "end_node": "路径点_39.906180_116.407600",
      "length": 0.0,
      "road_type": "路径移动",
      "road_name": "",
      "coordinates": [
        [
          39.90618000000006,
          116.40760000000012
        ],
        [
          39.90618000000006,
          116.40760000000012
        ]
      ],
      "traversal_count": 1,
      "created_time": "2025-11-10T21:24:05.874145",
      "last_traversed": "2025-11-10T21:24:05.874145",
      "speed_limit": 0,
      "road_condition": "良好"
    },
    "c815b323-11a9-414f-b3c3-fa7897cb6263": {
      "segment_id": "c815b323-11a9-414f-b3c3-fa7897cb6263",
      "start_node": "起始位置_39.906180_116.407600",
      "end_node": "道路位置_39.906180_116.407600",
      "length": 0.0,
      "road_type": "调整路径",
      "road_name": "",
      "coordinates": [
        [
          39.90618000000006,
          116.40760000000012
        ],
        [
          39.90618000000006,
          116.40760000000012
        ]
      ],
      "traversal_count": 1,
      "created_time": "2025-11-10T21:24:05.880776",
      "last_traversed": "2025-11-10T21:24:05.880776",
      "speed_limit": 0,
      "road_condition": "良好"
    },
    "f8251ae7-33fa-46ff-80c8-707c62029a51": {
      "segment_id": "f8251ae7-33fa-46ff-80c8-707c62029a51",
      "start_node": "segment_start_0",
      "end_node": "segment_end_0",
      "length": 0,
      "road_type": "决策节点",
      "road_name": "",
      "coordinates": [
        [
          39.90618000000006,
          116.40760000000012
        ]
      ],
      "traversal_count": 1,
      "created_time": "2025-11-10T21:24:05.882784",
      "last_traversed": "2025-11-10T21:24:05.882784",
      "speed_limit": 0,
      "road_condition": "良好"
    },
    "7ccfed2f-1ea3-4988-9387-42ae1ac4b2dd": {
      "segment_id": "7ccfed2f-1ea3-4988-9387-42ae1ac4b2dd",
      "start_node": "起始_39.906138_116.406611",
      "end_node": "路径点_39.906138_116.406611",
      "length": 0.0,
      "road_type": "路径移动",
      "road_name": "",
      "coordinates": [
        [
          39.90613805100003,
          116.40661135700009
        ],
        [
          39.90613805100003,
          116.40661135700009
        ]
      ],
      "traversal_count": 1,
      "created_time": "2025-11-10T21:24:12.737238",
      "last_traversed": "2025-11-10T21:24:12.737238",
      "speed_limit": 0,
      "road_condition": "良好"
    },
    "6dcad51f-5fc7-4801-8196-7d9a221c4bc0": {
      "segment_id": "6dcad51f-5fc7-4801-8196-7d9a221c4bc0",
      "start_node": "起始位置_39.906138_116.406611",
      "end_node": "道路位置_39.906138_116.406611",
      "length": 0.0,
      "road_type": "调整路径",
      "road_name": "",
      "coordinates": [
        [
          39.90613805100003,
          116.40661135700009
        ],
        [
          39.90613805100003,
          116.40661135700009
        ]
      ],
      "traversal_count": 1,
      "created_time": "2025-11-10T21:24:12.741800",
      "last_traversed": "2025-11-10T21:24:12.741800",
      "speed_limit": 0,
      "road_condition": "良好"
    }
  },
  "metadata": {
    "saved_time": "2025-11-10T21:24:12.741800",
    "operation_count": 10,
    "stats": {
      "poi_layer": {
        "total_connections": 0,
        "unique_pois": 0,
        "memory_type": "POI层记忆"
      },
      "node_layer": {
        "total_paths": 10,
        "total_nodes": 15,
        "average_path_length": 1.9,
        "total_distance": 19.38,
        "memory_type": "道路节点层记忆"
      },
      "road_layer": {
        "total_segments": 10,
        "total_nodes": 16,
        "total_distance": 19.38,
        "road_types": {
          "调整路径": {
            "count": 5,
            "total_length": 19.38367939306239
          },
          "路径移动": {
            "count": 4,
            "total_length": 0.0
          },
          "决策节点": {
            "count": 1,
            "total_length": 0
          }
        },
        "average_segment_length": 1.94,
        "memory_type": "道路数据层记忆"
      },
      "total_operations": 10,
      "last_updated": "2025-11-10T21:24:12.741800"
    }
  }
}