{
  "poi_connections": {},
  "node_sequences": {
    "94ac72d7-6a80-4aa6-928a-4a2bb8078986": {
      "path_id": "94ac72d7-6a80-4aa6-928a-4a2bb8078986",
      "nodes": [
        "起始位置_39.904200_116.407400",
        "道路位置_39.904026_116.407408"
      ],
      "coordinates": [
        [
          0.0,
          0.0
        ],
        [
          0.0,
          0.0
        ]
      ],
      "poi_waypoints": [],
      "start_location": [
        39.9042,
        116.4074
      ],
      "end_location": [
        39.904025779970134,
        116.40740775681562
      ],
      "total_distance": 19.38367939306239,
      "node_count": 2,
      "created_time": "2025-11-10T20:30:08.424536",
      "traversal_count": 1
    },
    "89bcf6e2-3480-4d6f-b230-8cb819c31bcf": {
      "path_id": "89bcf6e2-3480-4d6f-b230-8cb819c31bcf",
      "nodes": [
        "决策位置_39.904031_116.407525"
      ],
      "coordinates": [
        [
          0.0,
          0.0
        ]
      ],
      "poi_waypoints": [],
      "start_location": [
        39.90403100013058,
        116.40752500027864
      ],
      "end_location": [
        39.90403100013058,
        116.40752500027864
      ],
      "total_distance": 0.0,
      "node_count": 1,
      "created_time": "2025-11-10T20:30:09.561345",
      "traversal_count": 1
    },
    "67789381-b3b9-4335-9e0d-37af88ab711b": {
      "path_id": "67789381-b3b9-4335-9e0d-37af88ab711b",
      "nodes": [
        "起始_39.903785_116.407218",
        "路径点_39.903785_116.407218"
      ],
      "coordinates": [
        [
          0.0,
          0.0
        ],
        [
          0.0,
          0.0
        ]
      ],
      "poi_waypoints": [],
      "start_location": [
        39.90378500000003,
        116.40721800000006
      ],
      "end_location": [
        39.90378500000003,
        116.40721800000006
      ],
      "total_distance": 0.0,
      "node_count": 2,
      "created_time": "2025-11-10T20:30:16.421345",
      "traversal_count": 1
    },
    "41e94fbe-2ad2-4409-82a2-d5a9704ff0fb": {
      "path_id": "41e94fbe-2ad2-4409-82a2-d5a9704ff0fb",
      "nodes": [
        "起始位置_39.903785_116.407218",
        "道路位置_39.903785_116.407218"
      ],
      "coordinates": [
        [
          0.0,
          0.0
        ],
        [
          0.0,
          0.0
        ]
      ],
      "poi_waypoints": [],
      "start_location": [
        39.90378500000003,
        116.40721800000006
      ],
      "end_location": [
        39.90378500000003,
        116.40721800000006
      ],
      "total_distance": 0.0,
      "node_count": 2,
      "created_time": "2025-11-10T20:30:16.427954",
      "traversal_count": 1
    },
    "5b612441-9e1f-4f35-b1fb-a2ed01b074b7": {
      "path_id": "5b612441-9e1f-4f35-b1fb-a2ed01b074b7",
      "nodes": [
        "起始_39.903763_116.406714",
        "路径点_39.903763_116.406714"
      ],
      "coordinates": [
        [
          0.0,
          0.0
        ],
        [
          0.0,
          0.0
        ]
      ],
      "poi_waypoints": [],
      "start_location": [
        39.90376254800003,
        116.40671372700001
      ],
      "end_location": [
        39.90376254800003,
        116.40671372700001
      ],
      "total_distance": 0.0,
      "node_count": 2,
      "created_time": "2025-11-10T20:30:18.275468",
      "traversal_count": 1
    },
    "1d03d7b5-50ab-4730-a046-1f750319ec1c": {
      "path_id": "1d03d7b5-50ab-4730-a046-1f750319ec1c",
      "nodes": [
        "起始位置_39.903763_116.406714",
        "道路位置_39.903763_116.406714"
      ],
      "coordinates": [
        [
          0.0,
          0.0
        ],
        [
          0.0,
          0.0
        ]
      ],
      "poi_waypoints": [],
      "start_location": [
        39.90376254800003,
        116.40671372700001
      ],
      "end_location": [
        39.90376254800003,
        116.40671372700001
      ],
      "total_distance": 0.0,
      "node_count": 2,
      "created_time": "2025-11-10T20:30:18.282300",
      "traversal_count": 1
    },
    "fed11799-02a4-4e10-86d2-1afb1cb970ba": {
      "path_id": "fed11799-02a4-4e10-86d2-1afb1cb970ba",
      "nodes": [
        "起始_39.903386_116.406724",
        "路径点_39.903386_116.406724"
      ],
      "coordinates": [
        [
          0.0,
          0.0
        ],
        [
          0.0,
          0.0
        ]
      ],
      "poi_waypoints": [],
      "start_location": [
        39.903386459000046,
        116.40672444000006
      ],
      "end_location": [
        39.903386459000046,
        116.40672444000006
      ],
      "total_distance": 0.0,
      "node_count": 2,
      "created_time": "2025-11-10T20:30:20.098833",
      "traversal_count": 1
    },
    "8c0fb5f9-784a-49d5-963c-1deec8b5f85a": {
      "path_id": "8c0fb5f9-784a-49d5-963c-1deec8b5f85a",
      "nodes": [
        "起始位置_39.903386_116.406724",
        "道路位置_39.903386_116.406724"
      ],
      "coordinates": [
        [
          0.0,
          0.0
        ],
        [
          0.0,
          0.0
        ]
      ],
      "poi_waypoints": [],
      "start_location": [
        39.903386459000046,
        116.40672444000006
      ],
      "end_location": [
        39.903386459000046,
        116.40672444000006
      ],
      "total_distance": 0.0,
      "node_count": 2,
      "created_time": "2025-11-10T20:30:20.105404",
      "traversal_count": 1
    },
    "f48459b6-215c-44b0-8c0d-88559ff8eec5": {
      "path_id": "f48459b6-215c-44b0-8c0d-88559ff8eec5",
      "nodes": [
        "起始_39.903194_116.406724",
        "路径点_39.903194_116.406724"
      ],
      "coordinates": [
        [
          0.0,
          0.0
        ],
        [
          0.0,
          0.0
        ]
      ],
      "poi_waypoints": [],
      "start_location": [
        39.90319427800006,
        116.40672393300008
      ],
      "end_location": [
        39.90319427800006,
        116.40672393300008
      ],
      "total_distance": 0.0,
      "node_count": 2,
      "created_time": "2025-11-10T20:30:21.942511",
      "traversal_count": 1
    },
    "2347bffe-daae-421a-bf67-dc67e65efa87": {
      "path_id": "2347bffe-daae-421a-bf67-dc67e65efa87",
      "nodes": [
        "起始位置_39.903194_116.406724",
        "道路位置_39.903194_116.406724"
      ],
      "coordinates": [
        [
          0.0,
          0.0
        ],
        [
          0.0,
          0.0
        ]
      ],
      "poi_waypoints": [],
      "start_location": [
        39.90319427800006,
        116.40672393300008
      ],
      "end_location": [
        39.90319427800006,
        116.40672393300008
      ],
      "total_distance": 0.0,
      "node_count": 2,
      "created_time": "2025-11-10T20:30:21.949035",
      "traversal_count": 1
    },
    "5b225580-cc13-4f0f-a71f-7a2f02c79396": {
      "path_id": "5b225580-cc13-4f0f-a71f-7a2f02c79396",
      "nodes": [
        "起始_39.902267_116.406725",
        "路径点_39.902267_116.406725"
      ],
      "coordinates": [
        [
          0.0,
          0.0
        ],
        [
          0.0,
          0.0
        ]
      ],
      "poi_waypoints": [],
      "start_location": [
        39.902267091000056,
        116.40672462900011
      ],
      "end_location": [
        39.902267091000056,
        116.40672462900011
      ],
      "total_distance": 0.0,
      "node_count": 2,
      "created_time": "2025-11-10T20:30:23.788995",
      "traversal_count": 1
    },
    "1cb1715c-7107-4a42-9193-c0b1bd54ebda": {
      "path_id": "1cb1715c-7107-4a42-9193-c0b1bd54ebda",
      "nodes": [
        "起始位置_39.902267_116.406725",
        "道路位置_39.902267_116.406725"
      ],
      "coordinates": [
        [
          0.0,
          0.0
        ],
        [
          0.0,
          0.0
        ]
      ],
      "poi_waypoints": [],
      "start_location": [
        39.902267091000056,
        116.40672462900011
      ],
      "end_location": [
        39.902267091000056,
        116.40672462900011
      ],
      "total_distance": 0.0,
      "node_count": 2,
      "created_time": "2025-11-10T20:30:23.796996",
      "traversal_count": 1
    },
    "3f86dc3c-890a-415b-9f5e-c7b5c2534eca": {
      "path_id": "3f86dc3c-890a-415b-9f5e-c7b5c2534eca",
      "nodes": [
        "起始_39.902261_116.406338",
        "路径点_39.902261_116.406338"
      ],
      "coordinates": [
        [
          0.0,
          0.0
        ],
        [
          0.0,
          0.0
        ]
      ],
      "poi_waypoints": [],
      "start_location": [
        39.90226100000007,
        116.406338
      ],
      "end_location": [
        39.90226100000007,
        116.406338
      ],
      "total_distance": 0.0,
      "node_count": 2,
      "created_time": "2025-11-10T20:30:25.653665",
      "traversal_count": 1
    },
    "b46e8dbd-ec9b-4cfd-a8a4-c331953d2934": {
      "path_id": "b46e8dbd-ec9b-4cfd-a8a4-c331953d2934",
      "nodes": [
        "起始位置_39.902261_116.406338",
        "道路位置_39.902261_116.406338"
      ],
      "coordinates": [
        [
          0.0,
          0.0
        ],
        [
          0.0,
          0.0
        ]
      ],
      "poi_waypoints": [],
      "start_location": [
        39.90226100000007,
        116.406338
      ],
      "end_location": [
        39.90226100000007,
        116.406338
      ],
      "total_distance": 0.0,
      "node_count": 2,
      "created_time": "2025-11-10T20:30:25.660306",
      "traversal_count": 1
    },
    "a5d0aa85-c0b2-4363-86ea-2d8d56fcc1e2": {
      "path_id": "a5d0aa85-c0b2-4363-86ea-2d8d56fcc1e2",
      "nodes": [
        "决策位置_39.902261_116.406338"
      ],
      "coordinates": [
        [
          0.0,
          0.0
        ]
      ],
      "poi_waypoints": [],
      "start_location": [
        39.90226100000007,
        116.406338
      ],
      "end_location": [
        39.90226100000007,
        116.406338
      ],
      "total_distance": 0.0,
      "node_count": 1,
      "created_time": "2025-11-10T20:30:25.662308",
      "traversal_count": 1
    },
    "401dbe9c-e25c-4bc5-9ba4-e3e08b56c19e": {
      "path_id": "401dbe9c-e25c-4bc5-9ba4-e3e08b56c19e",
      "nodes": [
        "起始_39.902267_116.406725",
        "路径点_39.902267_116.406725"
      ],
      "coordinates": [
        [
          0.0,
          0.0
        ],
        [
          0.0,
          0.0
        ]
      ],
      "poi_waypoints": [],
      "start_location": [
        39.902267091000056,
        116.40672462900011
      ],
      "end_location": [
        39.902267091000056,
        116.40672462900011
      ],
      "total_distance": 0.0,
      "node_count": 2,
      "created_time": "2025-11-10T20:30:32.455205",
      "traversal_count": 1
    },
    "cbd3ae88-315b-4b55-8d33-7cddd7411c7b": {
      "path_id": "cbd3ae88-315b-4b55-8d33-7cddd7411c7b",
      "nodes": [
        "起始位置_39.902267_116.406725",
        "道路位置_39.902267_116.406725"
      ],
      "coordinates": [
        [
          0.0,
          0.0
        ],
        [
          0.0,
          0.0
        ]
      ],
      "poi_waypoints": [],
      "start_location": [
        39.902267091000056,
        116.40672462900011
      ],
      "end_location": [
        39.902267091000056,
        116.40672462900011
      ],
      "total_distance": 0.0,
      "node_count": 2,
      "created_time": "2025-11-10T20:30:32.462427",
      "traversal_count": 1
    },
    "49ce0458-9de9-4ec3-9616-1e2d7bdc8f0f": {
      "path_id": "49ce0458-9de9-4ec3-9616-1e2d7bdc8f0f",
      "nodes": [
        "起始_39.903194_116.406724",
        "路径点_39.903194_116.406724"
      ],
      "coordinates": [
        [
          0.0,
          0.0
        ],
        [
          0.0,
          0.0
        ]
      ],
      "poi_waypoints": [],
      "start_location": [
        39.90319427800006,
        116.40672393300008
      ],
      "end_location": [
        39.90319427800006,
        116.40672393300008
      ],
      "total_distance": 0.0,
      "node_count": 2,
      "created_time": "2025-11-10T20:30:34.306564",
      "traversal_count": 1
    },
    "5c0702d6-6b03-4939-b968-d81ca00b21a5": {
      "path_id": "5c0702d6-6b03-4939-b968-d81ca00b21a5",
      "nodes": [
        "起始位置_39.903194_116.406724",
        "道路位置_39.903194_116.406724"
      ],
      "coordinates": [
        [
          0.0,
          0.0
        ],
        [
          0.0,
          0.0
        ]
      ],
      "poi_waypoints": [],
      "start_location": [
        39.90319427800006,
        116.40672393300008
      ],
      "end_location": [
        39.90319427800006,
        116.40672393300008
      ],
      "total_distance": 0.0,
      "node_count": 2,
      "created_time": "2025-11-10T20:30:34.312579",
      "traversal_count": 1
    },
    "03e53ba7-955c-494f-a7b6-435dcf28422e": {
      "path_id": "03e53ba7-955c-494f-a7b6-435dcf28422e",
      "nodes": [
        "起始_39.903386_116.406724",
        "路径点_39.903386_116.406724"
      ],
      "coordinates": [
        [
          0.0,
          0.0
        ],
        [
          0.0,
          0.0
        ]
      ],
      "poi_waypoints": [],
      "start_location": [
        39.903386459000046,
        116.40672444000006
      ],
      "end_location": [
        39.903386459000046,
        116.40672444000006
      ],
      "total_distance": 0.0,
      "node_count": 2,
      "created_time": "2025-11-10T20:30:36.141285",
      "traversal_count": 1
    }
  },
  "road_segments": {
    "26ef7f31-a536-42c6-b6e9-d2e96c9dc4b2": {
      "segment_id": "26ef7f31-a536-42c6-b6e9-d2e96c9dc4b2",
      "start_node": "起始位置_39.904200_116.407400",
      "end_node": "道路位置_39.904026_116.407408",
      "length": 19.38367939306239,
      "road_type": "调整路径",
      "road_name": "",
      "coordinates": [
        [
          39.9042,
          116.4074
        ],
        [
          39.90403100013058,
          116.40752500027864
        ]
      ],
      "traversal_count": 1,
      "created_time": "2025-11-10T20:30:08.424536",
      "last_traversed": "2025-11-10T20:30:08.424536",
      "speed_limit": 0,
      "road_condition": "良好"
    },
    "fed48f5f-513b-4b43-ac13-96552f6a4cb7": {
      "segment_id": "fed48f5f-513b-4b43-ac13-96552f6a4cb7",
      "start_node": "segment_start_0",
      "end_node": "segment_end_0",
      "length": 0,
      "road_type": "决策节点",
      "road_name": "",
      "coordinates": [
        [
          39.90403100013058,
          116.40752500027864
        ]
      ],
      "traversal_count": 1,
      "created_time": "2025-11-10T20:30:09.561345",
      "last_traversed": "2025-11-10T20:30:09.561345",
      "speed_limit": 0,
      "road_condition": "良好"
    },
    "0c23bc2b-859b-4d1e-8f41-0e1538ce5bd8": {
      "segment_id": "0c23bc2b-859b-4d1e-8f41-0e1538ce5bd8",
      "start_node": "起始_39.903785_116.407218",
      "end_node": "路径点_39.903785_116.407218",
      "length": 0.0,
      "road_type": "路径移动",
      "road_name": "",
      "coordinates": [
        [
          39.90378500000003,
          116.40721800000006
        ],
        [
          39.90378500000003,
          116.40721800000006
        ]
      ],
      "traversal_count": 1,
      "created_time": "2025-11-10T20:30:16.421345",
      "last_traversed": "2025-11-10T20:30:16.421345",
      "speed_limit": 0,
      "road_condition": "良好"
    },
    "6085d68a-a1b7-4c6c-98d7-220be4c2cbe0": {
      "segment_id": "6085d68a-a1b7-4c6c-98d7-220be4c2cbe0",
      "start_node": "起始位置_39.903785_116.407218",
      "end_node": "道路位置_39.903785_116.407218",
      "length": 0.0,
      "road_type": "调整路径",
      "road_name": "",
      "coordinates": [
        [
          39.90378500000003,
          116.40721800000006
        ],
        [
          39.90378500000003,
          116.40721800000006
        ]
      ],
      "traversal_count": 1,
      "created_time": "2025-11-10T20:30:16.427954",
      "last_traversed": "2025-11-10T20:30:16.427954",
      "speed_limit": 0,
      "road_condition": "良好"
    },
    "542c0b6e-befe-40c8-8813-485f449c958f": {
      "segment_id": "542c0b6e-befe-40c8-8813-485f449c958f",
      "start_node": "起始_39.903763_116.406714",
      "end_node": "路径点_39.903763_116.406714",
      "length": 0.0,
      "road_type": "路径移动",
      "road_name": "",
      "coordinates": [
        [
          39.90376254800003,
          116.40671372700001
        ],
        [
          39.90376254800003,
          116.40671372700001
        ]
      ],
      "traversal_count": 1,
      "created_time": "2025-11-10T20:30:18.275468",
      "last_traversed": "2025-11-10T20:30:18.275468",
      "speed_limit": 0,
      "road_condition": "良好"
    },
    "02f0ad83-6990-4399-a64e-2d495ce1c3ee": {
      "segment_id": "02f0ad83-6990-4399-a64e-2d495ce1c3ee",
      "start_node": "起始位置_39.903763_116.406714",
      "end_node": "道路位置_39.903763_116.406714",
      "length": 0.0,
      "road_type": "调整路径",
      "road_name": "",
      "coordinates": [
        [
          39.90376254800003,
          116.40671372700001
        ],
        [
          39.90376254800003,
          116.40671372700001
        ]
      ],
      "traversal_count": 1,
      "created_time": "2025-11-10T20:30:18.282300",
      "last_traversed": "2025-11-10T20:30:18.282300",
      "speed_limit": 0,
      "road_condition": "良好"
    },
    "c2eaa548-1e30-4a19-9457-25f962f06081": {
      "segment_id": "c2eaa548-1e30-4a19-9457-25f962f06081",
      "start_node": "起始_39.903386_116.406724",
      "end_node": "路径点_39.903386_116.406724",
      "length": 0.0,
      "road_type": "路径移动",
      "road_name": "",
      "coordinates": [
        [
          39.903386459000046,
          116.40672444000006
        ],
        [
          39.903386459000046,
          116.40672444000006
        ]
      ],
      "traversal_count": 1,
      "created_time": "2025-11-10T20:30:20.098833",
      "last_traversed": "2025-11-10T20:30:20.098833",
      "speed_limit": 0,
      "road_condition": "良好"
    },
    "ccca82aa-6396-4ad2-bcce-0340f24383ff": {
      "segment_id": "ccca82aa-6396-4ad2-bcce-0340f24383ff",
      "start_node": "起始位置_39.903386_116.406724",
      "end_node": "道路位置_39.903386_116.406724",
      "length": 0.0,
      "road_type": "调整路径",
      "road_name": "",
      "coordinates": [
        [
          39.903386459000046,
          116.40672444000006
        ],
        [
          39.903386459000046,
          116.40672444000006
        ]
      ],
      "traversal_count": 1,
      "created_time": "2025-11-10T20:30:20.105404",
      "last_traversed": "2025-11-10T20:30:20.105404",
      "speed_limit": 0,
      "road_condition": "良好"
    },
    "7d317d57-3341-4ee8-8143-ce374b089d7f": {
      "segment_id": "7d317d57-3341-4ee8-8143-ce374b089d7f",
      "start_node": "起始_39.903194_116.406724",
      "end_node": "路径点_39.903194_116.406724",
      "length": 0.0,
      "road_type": "路径移动",
      "road_name": "",
      "coordinates": [
        [
          39.90319427800006,
          116.40672393300008
        ],
        [
          39.90319427800006,
          116.40672393300008
        ]
      ],
      "traversal_count": 1,
      "created_time": "2025-11-10T20:30:21.942511",
      "last_traversed": "2025-11-10T20:30:21.942511",
      "speed_limit": 0,
      "road_condition": "良好"
    },
    "2167cb79-5bfa-4042-aa1e-1bb0e206e69a": {
      "segment_id": "2167cb79-5bfa-4042-aa1e-1bb0e206e69a",
      "start_node": "起始位置_39.903194_116.406724",
      "end_node": "道路位置_39.903194_116.406724",
      "length": 0.0,
      "road_type": "调整路径",
      "road_name": "",
      "coordinates": [
        [
          39.90319427800006,
          116.40672393300008
        ],
        [
          39.90319427800006,
          116.40672393300008
        ]
      ],
      "traversal_count": 1,
      "created_time": "2025-11-10T20:30:21.949035",
      "last_traversed": "2025-11-10T20:30:21.949035",
      "speed_limit": 0,
      "road_condition": "良好"
    },
    "4f421659-96f1-406d-a3ab-f78c2c8427fe": {
      "segment_id": "4f421659-96f1-406d-a3ab-f78c2c8427fe",
      "start_node": "起始_39.902267_116.406725",
      "end_node": "路径点_39.902267_116.406725",
      "length": 0.0,
      "road_type": "路径移动",
      "road_name": "",
      "coordinates": [
        [
          39.902267091000056,
          116.40672462900011
        ],
        [
          39.902267091000056,
          116.40672462900011
        ]
      ],
      "traversal_count": 1,
      "created_time": "2025-11-10T20:30:23.788995",
      "last_traversed": "2025-11-10T20:30:23.788995",
      "speed_limit": 0,
      "road_condition": "良好"
    },
    "807c0646-f439-4d85-94ba-1f054885af58": {
      "segment_id": "807c0646-f439-4d85-94ba-1f054885af58",
      "start_node": "起始位置_39.902267_116.406725",
      "end_node": "道路位置_39.902267_116.406725",
      "length": 0.0,
      "road_type": "调整路径",
      "road_name": "",
      "coordinates": [
        [
          39.902267091000056,
          116.40672462900011
        ],
        [
          39.902267091000056,
          116.40672462900011
        ]
      ],
      "traversal_count": 1,
      "created_time": "2025-11-10T20:30:23.796996",
      "last_traversed": "2025-11-10T20:30:23.796996",
      "speed_limit": 0,
      "road_condition": "良好"
    },
    "d30c3162-a19e-43ea-a8ec-f7306a3fc11e": {
      "segment_id": "d30c3162-a19e-43ea-a8ec-f7306a3fc11e",
      "start_node": "起始_39.902261_116.406338",
      "end_node": "路径点_39.902261_116.406338",
      "length": 0.0,
      "road_type": "路径移动",
      "road_name": "",
      "coordinates": [
        [
          39.90226100000007,
          116.406338
        ],
        [
          39.90226100000007,
          116.406338
        ]
      ],
      "traversal_count": 1,
      "created_time": "2025-11-10T20:30:25.653665",
      "last_traversed": "2025-11-10T20:30:25.653665",
      "speed_limit": 0,
      "road_condition": "良好"
    },
    "c326756d-1230-4226-a731-2f2121aba7a2": {
      "segment_id": "c326756d-1230-4226-a731-2f2121aba7a2",
      "start_node": "起始位置_39.902261_116.406338",
      "end_node": "道路位置_39.902261_116.406338",
      "length": 0.0,
      "road_type": "调整路径",
      "road_name": "",
      "coordinates": [
        [
          39.90226100000007,
          116.406338
        ],
        [
          39.90226100000007,
          116.406338
        ]
      ],
      "traversal_count": 1,
      "created_time": "2025-11-10T20:30:25.660306",
      "last_traversed": "2025-11-10T20:30:25.660306",
      "speed_limit": 0,
      "road_condition": "良好"
    },
    "03e2bb56-1993-40d7-84ac-27d15bfe0e05": {
      "segment_id": "03e2bb56-1993-40d7-84ac-27d15bfe0e05",
      "start_node": "segment_start_0",
      "end_node": "segment_end_0",
      "length": 0,
      "road_type": "决策节点",
      "road_name": "",
      "coordinates": [
        [
          39.90226100000007,
          116.406338
        ]
      ],
      "traversal_count": 1,
      "created_time": "2025-11-10T20:30:25.662308",
      "last_traversed": "2025-11-10T20:30:25.662308",
      "speed_limit": 0,
      "road_condition": "良好"
    },
    "e012ac09-090a-48aa-879a-eda9ac2cb7ef": {
      "segment_id": "e012ac09-090a-48aa-879a-eda9ac2cb7ef",
      "start_node": "起始_39.902267_116.406725",
      "end_node": "路径点_39.902267_116.406725",
      "length": 0.0,
      "road_type": "路径移动",
      "road_name": "",
      "coordinates": [
        [
          39.902267091000056,
          116.40672462900011
        ],
        [
          39.902267091000056,
          116.40672462900011
        ]
      ],
      "traversal_count": 1,
      "created_time": "2025-11-10T20:30:32.455205",
      "last_traversed": "2025-11-10T20:30:32.455205",
      "speed_limit": 0,
      "road_condition": "良好"
    },
    "470368be-3f1b-479f-8fb7-caf003047ec8": {
      "segment_id": "470368be-3f1b-479f-8fb7-caf003047ec8",
      "start_node": "起始位置_39.902267_116.406725",
      "end_node": "道路位置_39.902267_116.406725",
      "length": 0.0,
      "road_type": "调整路径",
      "road_name": "",
      "coordinates": [
        [
          39.902267091000056,
          116.40672462900011
        ],
        [
          39.902267091000056,
          116.40672462900011
        ]
      ],
      "traversal_count": 1,
      "created_time": "2025-11-10T20:30:32.462427",
      "last_traversed": "2025-11-10T20:30:32.462427",
      "speed_limit": 0,
      "road_condition": "良好"
    },
    "0d49f32d-496e-4b7e-89b7-575d16236399": {
      "segment_id": "0d49f32d-496e-4b7e-89b7-575d16236399",
      "start_node": "起始_39.903194_116.406724",
      "end_node": "路径点_39.903194_116.406724",
      "length": 0.0,
      "road_type": "路径移动",
      "road_name": "",
      "coordinates": [
        [
          39.90319427800006,
          116.40672393300008
        ],
        [
          39.90319427800006,
          116.40672393300008
        ]
      ],
      "traversal_count": 1,
      "created_time": "2025-11-10T20:30:34.306564",
      "last_traversed": "2025-11-10T20:30:34.306564",
      "speed_limit": 0,
      "road_condition": "良好"
    },
    "b548d619-1933-4e36-828a-6cbd0f2f93b3": {
      "segment_id": "b548d619-1933-4e36-828a-6cbd0f2f93b3",
      "start_node": "起始位置_39.903194_116.406724",
      "end_node": "道路位置_39.903194_116.406724",
      "length": 0.0,
      "road_type": "调整路径",
      "road_name": "",
      "coordinates": [
        [
          39.90319427800006,
          116.40672393300008
        ],
        [
          39.90319427800006,
          116.40672393300008
        ]
      ],
      "traversal_count": 1,
      "created_time": "2025-11-10T20:30:34.313564",
      "last_traversed": "2025-11-10T20:30:34.313564",
      "speed_limit": 0,
      "road_condition": "良好"
    },
    "c063d5bb-bb8f-4fcb-a3ac-624cec65d16f": {
      "segment_id": "c063d5bb-bb8f-4fcb-a3ac-624cec65d16f",
      "start_node": "起始_39.903386_116.406724",
      "end_node": "路径点_39.903386_116.406724",
      "length": 0.0,
      "road_type": "路径移动",
      "road_name": "",
      "coordinates": [
        [
          39.903386459000046,
          116.40672444000006
        ],
        [
          39.903386459000046,
          116.40672444000006
        ]
      ],
      "traversal_count": 1,
      "created_time": "2025-11-10T20:30:36.141285",
      "last_traversed": "2025-11-10T20:30:36.141285",
      "speed_limit": 0,
      "road_condition": "良好"
    }
  },
  "metadata": {
    "saved_time": "2025-11-10T20:30:36.141285",
    "operation_count": 20,
    "stats": {
      "poi_layer": {
        "total_connections": 0,
        "unique_pois": 0,
        "memory_type": "POI层记忆"
      },
      "node_layer": {
        "total_paths": 20,
        "total_nodes": 28,
        "average_path_length": 1.9,
        "total_distance": 19.38,
        "memory_type": "道路节点层记忆"
      },
      "road_layer": {
        "total_segments": 20,
        "total_nodes": 28,
        "total_distance": 19.38,
        "road_types": {
          "调整路径": {
            "count": 9,
            "total_length": 19.38367939306239
          },
          "决策节点": {
            "count": 2,
            "total_length": 0
          },
          "路径移动": {
            "count": 9,
            "total_length": 0.0
          }
        },
        "average_segment_length": 0.97,
        "memory_type": "道路数据层记忆"
      },
      "total_operations": 20,
      "last_updated": "2025-11-10T20:30:36.141285"
    }
  }
}